{"kind":"APIResourceList","apiVersion":"v1","groupVersion":"work.open-cluster-management.io/v1","resources":[{"name":"appliedmanifestworks","singularName":"appliedmanifestwork","namespaced":false,"group":"work.open-cluster-management.io","version":"v1","kind":"AppliedManifestWork","verbs":["delete","deletecollection","get","list","patch","create","update","watch"]},{"name":"appliedmanifestworks/status","singularName":"appliedmanifestwork","namespaced":false,"group":"work.open-cluster-management.io","version":"v1","kind":"AppliedManifestWork","verbs":["get","patch","update"]},{"name":"manifestworks","singularName":"manifestwork","namespaced":true,"group":"work.open-cluster-management.io","version":"v1","kind":"ManifestWork","verbs":["delete","deletecollection","get","list","patch","create","update","watch"]},{"name":"manifestworks/status","singularName":"manifestwork","namespaced":true,"group":"work.open-cluster-management.io","version":"v1","kind":"ManifestWork","verbs":["get","patch","update"]}]}
