{"kind":"APIResourceList","apiVersion":"v1","groupVersion":"k8gb.io/v1beta1","resources":[{"name":"gslbs","singularName":"gslb","namespaced":true,"group":"k8gb.io","version":"v1beta1","kind":"Gslb","verbs":["delete","deletecollection","get","list","patch","create","update","watch"]},{"name":"gslbs/status","singularName":"gslb","namespaced":true,"group":"k8gb.io","version":"v1beta1","kind":"Gslb","verbs":["get","patch","update"]},{"name":"zonedelegations","singularName":"zonedelegation","namespaced":false,"group":"k8gb.io","version":"v1beta1","kind":"ZoneDelegation","verbs":["delete","deletecollection","get","list","patch","create","update","watch"],"shortNames":["zd"]},{"name":"zonedelegations/status","singularName":"zonedelegation","namespaced":false,"group":"k8gb.io","version":"v1beta1","kind":"ZoneDelegation","verbs":["get","patch","update"]}]}
